.gitignore
.travis.yml
CHANGES.rst
README.rst
setup.cfg
setup.py
tox.ini
docs/Makefile
docs/api.rst
docs/conf.py
docs/index.rst
walkabout/__init__.py
walkabout/tests.py
walkabout.egg-info/PKG-INFO
walkabout.egg-info/SOURCES.txt
walkabout.egg-info/dependency_links.txt
walkabout.egg-info/not-zip-safe
walkabout.egg-info/requires.txt
walkabout.egg-info/top_level.txt